odoo/addons/bank_statement_journal_items/README.rst
odoo/addons/bank_statement_journal_items/__init__.py
odoo/addons/bank_statement_journal_items/__manifest__.py
odoo/addons/bank_statement_journal_items/i18n/bank_statement_journal_items.pot
odoo/addons/bank_statement_journal_items/models/__init__.py
odoo/addons/bank_statement_journal_items/models/account_bank_statement.py
odoo/addons/bank_statement_journal_items/readme/CONTRIBUTORS.rst
odoo/addons/bank_statement_journal_items/readme/DESCRIPTION.rst
odoo/addons/bank_statement_journal_items/static/description/icon.png
odoo/addons/bank_statement_journal_items/static/description/index.html
odoo/addons/bank_statement_journal_items/views/bank_statement.xml
odoo13_addon_bank_statement_journal_items-13.0.1.0.1.dist-info/METADATA
odoo13_addon_bank_statement_journal_items-13.0.1.0.1.dist-info/WHEEL
odoo13_addon_bank_statement_journal_items-13.0.1.0.1.dist-info/top_level.txt
odoo13_addon_bank_statement_journal_items-13.0.1.0.1.dist-info/RECORD
