Metadata-Version: 2.1
Name: odoo13-addon-bank-statement-journal-items
Version: 13.0.1.0.1
Summary: Add Journal Items button in the bank statements
Home-page: http://www.github.com/OCA/account-reconcile
Author: Camptocamp, Odoo Community Association (OCA)
Author-email: support@odoo-community.org
License: AGPL-3
Platform: UNKNOWN
Classifier: Programming Language :: Python
Classifier: Framework :: Odoo
Classifier: License :: OSI Approved :: GNU Affero General Public License v3
Requires-Python: >=3.5
Requires-Dist: odoo (<13.1dev,>=13.0a)
